{
  "$mulmocast": {
    "version": "1.0",
    "credit": "closing"
  },
  "title": "Tascale：時間を取り戻す魔法のツール",
  "lang": "ja",
  "canvasSize": {
    "width": 1536,
    "height": 1024
  },
  "imageParams": {
    "style": "<style>A multi panel comic strip. Ghibli style. The presenter is a 30-year-old man with dark short hair and glasses.</style>"
  },
  "references": [],
  "beats": [
    {
      "text": "僕はフリーランスのディレクター。Webサイト制作や広告運用の管理を任されている。ありがたいことにすごく忙しい毎日だ。"
    },
    {
      "text": "僕の立場は複雑で、上流には直クライアントや広告代理店、下流にはデザイナーやエンジニア、ライターがいる。"
    },
    {
      "text": "いろんな要望や指示、依頼、相談、交渉が僕を通じてたくさんの人に向かう。それらを把握するだけでも本当に大変なんだ。"
    },
    {
      "text": "Slack、チャットワーク、LINE、SMS、メール...。様々なツールから連絡が飛んできて、受信するたびにタスクが増えていく。"
    },
    {
      "text": "さらに、他の人のプロジェクトにアサインされたり、僕がプロジェクトをつくってすべてを管理することもある。"
    },
    {
      "text": "上流から降りてくる自分のタスク、自分でつくった自分のタスク、そして自分がお願いするメンバーのタスク。"
    },
    {
      "text": "それらをすべて管理しなくてはいけない。とにかく自分が関係するすべての「タスク」を俯瞰して見たいんだ。"
    },
    {
      "text": "Googleカレンダー？タスク管理にはUIがカレンダーすぎる。"
    },
    {
      "text": "AsanaやBacklog？あんなに複雑である必要はないし、簡単に共有できないからNG。"
    },
    {
      "text": "クライアントにいちいちアカウント作ってもらうあんてありえない。もっと簡単に操作と共有ができるツールが必要だよ。"
    },
    {
      "text": "もちろんAIのアシストもほしい。タスクが重なりすぎて破綻しそうなところを指摘してくれるとか。"
    },
    {
      "text": "スケジュールに遅れが出そうなときには教えてくれて、さらにアドバイスもくれるし、その変更もすごく簡単。"
    },
    {
      "text": "それが、僕たちがつくる理想のスケジュール&プロジェクト管理アシスタント「Tascale」。これが解決策だ。"
    },
    {
      "text": "これで僕はGoogleカレンダーに仕事の予定を入れなくて済む。クライアントやパートナーとも簡単にスケジュールを共有できる。"
    },
    {
      "text": "そして僕は、目の前の本当にやらなければいけないことに集中できる。もっと仕事を楽しめるようになる。"
    },
    {
      "text": "そんな日が、もうそこまで来ている。Tascaleで時間を取り戻そう。"
    }
  ]
}